[
  {
    "Id": "1074806",
    "ThreadId": "451893",
    "Html": "I need to implement the heatmap series in D3. I don't find it in the WPF version. The sample on the site is Silverlight. \r<br />\n<br />\nDoes the WPF version have the heatmap series?\r<br />\n<br />\nThanks<br />\n",
    "PostedDate": "2013-07-30T11:28:10.223-07:00",
    "UserRole": null,
    "MarkedAsAnswerDate": null
  },
  {
    "Id": "1076900",
    "ThreadId": "451893",
    "Html": "i am facing the same situation. looks like heatmap is only in sliverlight version, which sucks. <br />\n",
    "PostedDate": "2013-08-05T12:12:23.987-07:00",
    "UserRole": null,
    "MarkedAsAnswerDate": null
  },
  {
    "Id": "1076902",
    "ThreadId": "451893",
    "Html": "\r\n<div>\r\n<p><span style=\"font-size:11.0pt; font-family:\">What is your next step? Still looking for a tool like D3?</span></p>\r\n<p><span style=\"font-size:11.0pt; font-family:\">I’m working with OxyPlot, but it has problems. Started looking at ChartDirector. Looks like it does a lot, but it costs.</span></p>\r\n<p><span style=\"font-size:11.0pt; font-family:\"></span></p>\r\n<p><span style=\"font-size:11.0pt; font-family:\">I may end up writing my own heat map stuff. My biggest problem is trying to generate a heat map/contour of an unstructured grid. But from all my research, everyone convert unstructured to structured. I have to\r\n figure out how to do that.</span></p>\r\n<p><span style=\"font-size:11.0pt; font-family:\"></span></p>\r\n<p><span style=\"font-size:11.0pt; font-family:\">Michael</span></p>\r\n<p><span style=\"font-size:11.0pt; font-family:\"></span></p>\r\n<div>\r\n<div style=\"border:none; border-top:solid #B5C4DF 1.0pt; padding:3.0pt 0in 0in 0in\">\r\n<p><b><span style=\"font-size:10.0pt; font-family:\"></span></b></p>\r\n</div>\r\n</div>\r\n</div>\r\n",
    "PostedDate": "2013-08-05T12:16:45.25-07:00",
    "UserRole": null,
    "MarkedAsAnswerDate": null
  }
]