[
  {
    "Id": "1122393",
    "ThreadId": "468267",
    "Html": "Hi,<br />\n<br />\nI am new o use this library hence need help.<br />\n<br />\nWhat is latest stable version of this library which contains all the functionalisties? I found FitToViewRestriction is not added in some version hence needed this information.<br />\n<br />\nFrom where to get the latest and stable version?<br />\n<br />\nIs there any document or note on latest version and how to use it?<br />\n<br />\nVishal N<br />\n",
    "PostedDate": "2013-11-12T07:36:23.497-08:00",
    "UserRole": null,
    "MarkedAsAnswerDate": null
  }
]